{
   "2017":{
      "SP":{
         "name":"Saraswati Puja 2017",
         "isCurrentEvent":"Y",
         "venue":"Bishop Ireton Center",
         "date":"02-04-2017 08:00:00",
         "time":"8AM to 10PM",
         "code":"SP",
         "address":{
            "street":"3300 Old Courthouse Rd",
            "city":"North Chesterfield",
            "state":"VA",
            "zip":"23236"
         },
         "lastOnlineDateRegistration":"02-03-2017 11:59:59",
         "committeeMembers":{
            "pujaCommittee":{
               "htmlLabel":"Puja Committee",
               "members":"Baishakhy Chakraborty,Chaitali Roy,Karabi Saha"
            },
            "foodCommittee":{
               "htmlLabel":"Food Committee",
               "members":"Suronita Dasbiswas,Sucheta Mukherjee,Sayani Nandi,Manisha Prasad,Poulami Saha"
            },
            "culturalCommittee":{
               "htmlLabel":"Cultural Committee",
               "members":"Bhaswati Datta,Reshmi Ghosh,Trina Dutta"
            },
            "pujaDecorations":{
               "htmlLabel":"Puja Decoration",
               "members":"Sanghamitra Gayali,Dilip Chakravarty,Swati Neogi,Debarati Pradhan,Ridhi Biswas Mukherjee"
            },
            "logisticsTeam":{
               "htmlLabel":"Logistics",
               "members":"Rahul Moray,Samrat Ghosh"
            },
            "facilitiesCoordinator":{
               "htmlLabel":"Sound Coordinator",
               "members":"Tapabrata Pal,Ashish Roy,Arjoo Bandopadhyay"
            },
            "registrationAndFrontDesk":{
               "htmlLabel":"Front Desk",
               "members":"Soumen Pradhan,Arko Chakraborty"
            },
            "webTeam":{
               "htmlLabel":"Web Team",
               "members":"Abhishek Ghosh,Sandipan Biswas,Pritam Sarkar"
            }
         },
         "earlyBird":{
            "date":"01-28-2017 11:59:59",
            "fee":{
               "student":{
                  "member":{
                     "single":20,
                     "family":35
                  },
                  "nonmember":{
                     "single":25,
                     "family":45
                  }
               },
               "nonStudent":{
                  "member":{
                     "single":35,
                     "family":65
                  },
                  "nonmember":{
                     "single":45,
                     "family":75
                  }
               }
            }
         },
         "afterEarlyBird":{
            "fee":{
               "student":{
                  "member":{
                     "single":25,
                     "family":45
                  },
                  "nonmember":{
                     "single":30,
                     "family":55
                  }
               },
               "nonStudent":{
                  "member":{
                     "single":45,
                     "family":75
                  },
                  "nonmember":{
                     "single":55,
                     "family":85
                  }
               }
            }
         },
         "food":{
            "1":{
               "lunch":{
                  "veg":"Rice, Daal",
                  "nonVeg":"Chicken",
                  "kid":"Luchi"
               },
               "dinner":{
                  "veg":"Paneer",
                  "nonVeg":"Biriyani, Mutton",
                  "kid":"Kachuri,pizza"
               }
            }
         },
         "eventsOfTheday":{
            "1":[
               {
                  "label":"Puja Starts & Dagger",
                  "time":"10:00 am",
				  "order" : 1
               },
               {
                  "label":"Prasad Distribution",
                  "time":"12:00 pm",
				  "order" : 2
               },
               {
                  "label":"Lunch",
                  "time":"1:00 pm",
				  "order" : 3
               },
			   {
                  "label":"Dinner",
                  "time":"8:00 pm",
				  "order" : 5
               },
               {
                  "label":"Evening Snacks",
                  "time":"5:00 pm",
				  "order" : 4
               }
               
            ]
         },
         "culturalPrograms":{
            "1":[
               {
                  "order":2,
                  "time":"07:00 pm",
                  "duration":"30m",
                  "participants":[
                     "names"
                  ],
                  "programName":"Some Program2",
                  "programDescription":"Some Program description2"
               },
               {
                  "order":1,
                  "time":"08:00 pm",
                  "duration":"1hr",
                  "participants":[
                     "names"
                  ],
                  "programName":"Some Program1",
                  "programDescription":"Some Program description1"
               }
            ]
         }
      },
      "DP":{
         "name":"Durga Puja 2017",
         "venue":"Bishop Ireton Center",
         "date":"February 4, 2017",
         "time":"8AM to 10PM",
         "code":"DP",
         "address":{
            "street":"3300 Old Courthouse Rd",
            "city":"North Chesterfield",
            "state":"VA",
            "zip":"23236"
         },
         "lastOnlineDateRegistration":"01-12-2017 11:59:59",
         "earlyBird":{
            "date":"12-30-2017 11:59:59",
            "fee":{
               "student":{
                  "member":{
                     "single":50,
                     "family":60
                  },
                  "nonmember":{
                     "single":70,
                     "family":80
                  }
               },
               "nonStudent":{
                  "member":{
                     "single":90,
                     "family":100
                  },
                  "nonmember":{
                     "single":110,
                     "family":120
                  }
               }
            }
         },
         "afterEarlyBird":{
            "fee":{
               "student":{
                  "member":{
                     "single":130,
                     "family":140
                  },
                  "nonmember":{
                     "single":150,
                     "family":160
                  }
               },
               "nonStudent":{
                  "member":{
                     "single":170,
                     "family":180
                  },
                  "nonmember":{
                     "single":190,
                     "family":200
                  }
               }
            }
         }
      }
   },
   "2018":{
      "SP":{
         "name":"Saraswati Puja 2018",
         "venue":"Bishop Ireton Center",
         "date":"February 4, 2018",
         "time":"8AM to 10PM",
         "code":"SP",
         "address":{
            "street":"3300 Old Courthouse Rd",
            "city":"North Chesterfield",
            "state":"VA",
            "zip":"23236"
         },
         "lastOnlineDateRegistration":"01-12-2018 11:59:59",
         "afterEarlyBird":{
            "fee":{
               "student":{
                  "member":{
                     "single":40,
                     "family":80
                  },
                  "nonmember":{
                     "single":50,
                     "family":90
                  }
               },
               "nonStudent":{
                  "member":{
                     "single":40,
                     "family":80
                  },
                  "nonmember":{
                     "single":50,
                     "family":90
                  }
               }
            }
         }
      },
      "DP":{
         "name":"Durga Puja 2018",
         "venue":"Bishop Ireton Center",
         "date":"February 4, 2018",
         "time":"8AM to 10PM",
         "code":"DP",
         "address":{
            "street":"3300 Old Courthouse Rd",
            "city":"North Chesterfield",
            "state":"VA",
            "zip":"23236"
         },
         "lastOnlineDateRegistration":"01-12-2018 11:59:59",
         "earlyBird":{
            "date":"12-30-2018 11:59:59",
            "fee":{
               "student":{
                  "member":{
                     "single":40,
                     "family":80
                  },
                  "nonmember":{
                     "single":50,
                     "family":90
                  }
               },
               "nonStudent":{
                  "member":{
                     "single":40,
                     "family":80
                  },
                  "nonmember":{
                     "single":50,
                     "family":90
                  }
               }
            }
         },
         "afterEarlyBird":{
            "fee":{
               "student":{
                  "member":{
                     "single":40,
                     "family":80
                  },
                  "nonmember":{
                     "single":50,
                     "family":90
                  }
               },
               "nonStudent":{
                  "member":{
                     "single":40,
                     "family":80
                  },
                  "nonmember":{
                     "single":50,
                     "family":90
                  }
               }
            }
         },
         "sponsorship":{
            "Platinum":200,
            "Gold":100,
            "Silver":80,
            "Bronze":60
         }
      }
   }
}
